organize_photos-0.1.0.dist-info/METADATA
organize_photos-0.1.0.dist-info/WHEEL
organize_photos-0.1.0.dist-info/entry_points.txt
organize_photos-0.1.0.dist-info/licenses/LICENSE
organize_photos/__init__.py
organize_photos/__main__.py
organize_photos/cli.py
organize_photos/constants.py
organize_photos/fileinfo.py
organize_photos/loader.py
organize_photos/processing.py
organize_photos/py.typed
organize_photos/template_backport.py
organize_photos-0.1.0.dist-info/RECORD
