Metadata-Version: 2.1
Name: organize-photos
Version: 0.1.0
Summary: Python CLI program that allows you to organize your photos into subfolders based on their EXIF metadata.
Keywords: photos images multimedia organize exif
Author-Email: ohmycoffe <ohmycoffe1@gmail.com>
License: MIT License
Classifier: Development Status :: 3 - Alpha
Classifier: Environment :: Console
Classifier: Intended Audience :: End Users/Desktop
Classifier: Operating System :: OS Independent
Classifier: Programming Language :: Python
Classifier: Programming Language :: Python :: 3
Classifier: Programming Language :: Python :: 3.8
Classifier: Programming Language :: Python :: 3.9
Classifier: Programming Language :: Python :: 3.10
Classifier: Programming Language :: Python :: 3.11
Classifier: Topic :: Multimedia :: Graphics
Classifier: Topic :: Utilities
Classifier: License :: OSI Approved :: MIT License
Project-URL: Repository, https://github.com/ohmycoffe/organize-photos
Requires-Python: >=3.8
Requires-Dist: Pillow>=10.0.1
Requires-Dist: click>=8.1.7
